rustic_ai/redis/__init__.py
rustic_ai/redis/agent_ext/__init__.py
rustic_ai/redis/agent_ext/kvstore.py
rustic_ai/redis/messaging/__init__.py
rustic_ai/redis/messaging/backend.py
rustic_ai/redis/messaging/connection_manager.py
rustic_ai/redis/messaging/exceptions.py
rustic_ai/redis/messaging/message_store.py
rustic_ai/redis/messaging/pubsub_manager.py
rustic_ai/redis/messaging/retry_utils.py
rustic_ai/redis/state/__init__.py
rustic_ai/redis/state/manager.py
rusticai_redis-1.0.0.dist-info/METADATA
rusticai_redis-1.0.0.dist-info/WHEEL
rusticai_redis-1.0.0.dist-info/RECORD
